{
  "data": [
    {
      "name": "NeoGrowth",
      "src": "../../../../assets/img/page/clients/neogrowth.png",
      "link": ""
    },
    {
      "name": "Zest Money",
      "src": "../../../../assets/img/page/clients/zest-money.png",
      "link": ""
    },
    {
      "name": "PayU Money",
      "src": "../../../../assets/img/page/clients/payu-money.png",
      "link": ""
    },
    {
      "name": "Muthoot Fincorp",
      "src": "../../../../assets/img/page/clients/muthoot-fincorp.png",
      "link": ""
    },
    {
      "name": "FlexiLoans",
      "src": "../../../../assets/img/page/clients/flexi-loans.png",
      "link": ""
    },
    {
      "name": "CreditWise",
      "src": "../../../../assets/img/page/clients/credit-wise.png",
      "link": ""
    },
    {
      "name": "FairCent",
      "src": "../../../../assets/img/page/clients/faircent.png",
      "link": ""
    },
    {
      "name": "Rupeelend",
      "src": "../../../../assets/img/page/clients/rupeelend.png",
      "link": ""
    },
    {
      "name": "Early Salary",
      "src": "../../../../assets/img/page/clients/early-salary.png",
      "link": ""
    }
  ]
}
